giza/cli/__init__.py
giza/cli/__main__.py
giza/cli/callbacks.py
giza/cli/cli.py
giza/cli/client.py
giza/cli/commands/__init__.py
giza/cli/commands/actions.py
giza/cli/commands/agents.py
giza/cli/commands/endpoints.py
giza/cli/commands/models.py
giza/cli/commands/prove.py
giza/cli/commands/reset_password.py
giza/cli/commands/users.py
giza/cli/commands/verify.py
giza/cli/commands/version.py
giza/cli/commands/versions.py
giza/cli/commands/workspaces.py
giza/cli/exceptions.py
giza/cli/frameworks/__init__.py
giza/cli/frameworks/cairo.py
giza/cli/frameworks/ezkl.py
giza/cli/options.py
giza/cli/py.typed
giza/cli/schemas/agents.py
giza/cli/schemas/endpoints.py
giza/cli/schemas/jobs.py
giza/cli/schemas/logs.py
giza/cli/schemas/message.py
giza/cli/schemas/models.py
giza/cli/schemas/proofs.py
giza/cli/schemas/token.py
giza/cli/schemas/users.py
giza/cli/schemas/verify.py
giza/cli/schemas/versions.py
giza/cli/schemas/workspaces.py
giza/cli/utils/__init__.py
giza/cli/utils/decorators.py
giza/cli/utils/echo.py
giza/cli/utils/enums.py
giza/cli/utils/exception_handling.py
giza/cli/utils/misc.py
giza_cli-0.18.1.dist-info/LICENSE
giza_cli-0.18.1.dist-info/METADATA
giza_cli-0.18.1.dist-info/WHEEL
giza_cli-0.18.1.dist-info/entry_points.txt
giza_cli-0.18.1.dist-info/RECORD
